{
  "image": "image_74920.jpg",
  "frame_index": 74920,
  "timestamp_ns": 1749051443425883111,
  "gps": {
    "timestamp_ns": 1749051443358166980,
    "lat": 36.21317710759261,
    "lon": -79.80461158232218,
    "hgt": 266.08553122822195,
    "lat_stdev": 1.3605380058288574,
    "lon_stdev": 0.8471505045890808,
    "hgt_stdev": 3.000308036804199,
    "num_svs": 20,
    "num_sol_svs": 8,
    "hdop": null,
    "vdop": null,
    "undulation": -32.79999923706055,
    "diff_age": 6.0,
    "sol_age": 0.0
  },
  "connectivity": {
    "avg_d_mbps": 1131.543,
    "avg_u_mbps": 63.554,
    "avg_latency_ms": 17.0,
    "avg_download_latency_ms": 17.0,
    "avg_upload_latency_ms": 17.0,
    "tests": 3,
    "source": "nearest"
  },
  "connectivity_error": null,
  "evaluation": {
    "lane": {
      "score": 0.99,
      "valid_lane_lines": 5,
      "selected_threshold": 0.25,
      "geometry_space": "warped_px",
      "best_threshold_detail": {
        "threshold": 0.25,
        "selected_curves": [
          [
            82.3876,
            164.054,
            88.3161,
            161.664,
            93.9441,
            159.396,
            99.2937,
            157.24,
            104.385,
            155.187,
            109.236,
            153.231,
            113.863,
            151.365,
            118.281,
            149.584,
            122.504,
            147.88,
            126.543,
            146.25,
            130.411,
            144.688,
            134.119,
            143.191,
            137.674,
            141.754,
            141.088,
            140.374,
            144.372,
            139.048,
            147.539,
            137.772,
            150.6,
            136.544,
            153.566,
            135.361,
            156.447,
            134.221,
            159.252,
            133.121,
            161.99,
            132.059,
            164.67,
            131.034,
            167.298,
            130.043,
            169.881,
            129.085,
            172.427,
            128.158,
            174.94,
            127.261,
            177.42,
            126.392,
            179.862,
            125.549,
            182.262,
            124.733,
            184.615,
            123.941,
            186.919,
            123.173,
            189.169,
            122.427,
            191.362,
            121.703,
            193.495,
            120.999,
            195.564,
            120.315,
            197.568,
            119.649,
            199.503,
            119.002,
            201.367,
            118.372,
            203.162,
            117.759,
            204.891,
            117.162,
            206.559,
            116.58,
            208.17,
            116.013,
            209.728,
            115.461,
            211.236,
            114.922,
            212.698,
            114.396,
            214.117,
            113.883,
            215.497,
            113.383,
            216.839,
            112.894,
            218.148,
            112.417,
            218.919,
            112.136
          ],
          [
            17.0566,
            289.075,
            34.6083,
            276.228,
            50.199,
            264.816,
            64.1415,
            254.613,
            76.6857,
            245.436,
            88.0335,
            237.137,
            98.35,
            229.597,
            107.771,
            222.716,
            116.411,
            216.41,
            124.364,
            210.612,
            131.712,
            205.261,
            138.521,
            200.308,
            144.852,
            195.711,
            150.755,
            191.431,
            156.273,
            187.438,
            161.445,
            183.704,
            166.304,
            180.204,
            170.88,
            176.917,
            175.197,
            173.823,
            179.279,
            170.907,
            183.145,
            168.154,
            186.813,
            165.55,
            190.299,
            163.083,
            193.615,
            160.743,
            196.776,
            158.52,
            199.792,
            156.407,
            202.674,
            154.394,
            205.43,
            152.475,
            208.07,
            150.643,
            210.602,
            148.893,
            213.031,
            147.219,
            215.365,
            145.617,
            217.61,
            144.081,
            219.771,
            142.609,
            221.852,
            141.195,
            223.86,
            139.837,
            225.797,
            138.532,
            227.667,
            137.275,
            229.474,
            136.066,
            231.22,
            134.9,
            232.908,
            133.776,
            234.54,
            132.692,
            236.118,
            131.645,
            237.646,
            130.633,
            239.124,
            129.656,
            240.554,
            128.71,
            241.939,
            127.795,
            243.28,
            126.91,
            244.579,
            126.052,
            245.836,
            125.22,
            247.054,
            124.413,
            248.233,
            123.631,
            249.375,
            122.872,
            250.481,
            122.135,
            251.552,
            121.419,
            252.59,
            120.723,
            253.596,
            120.046,
            254.572,
            119.388,
            255.52,
            118.748,
            256.44,
            118.125,
            257.334,
            117.518,
            258.203,
            116.927,
            259.048,
            116.352,
            259.87,
            115.791,
            260.671,
            115.244,
            261.45,
            114.71,
            262.21,
            114.19,
            262.951,
            113.682,
            263.674,
            113.186,
            264.379,
            112.702,
            265.068,
            112.229,
            265.204,
            112.136
          ],
          [
            85.5717,
            337.521,
            103.536,
            318.547,
            119.104,
            302.104,
            132.724,
            287.718,
            144.742,
            275.026,
            155.424,
            263.745,
            164.982,
            253.652,
            173.584,
            244.569,
            181.367,
            236.351,
            188.443,
            228.881,
            194.905,
            222.06,
            200.829,
            215.809,
            206.28,
            210.057,
            211.313,
            204.748,
            215.974,
            199.833,
            220.303,
            195.269,
            224.335,
            191.02,
            228.099,
            187.054,
            231.622,
            183.344,
            234.926,
            179.866,
            238.031,
            176.599,
            240.955,
            173.524,
            243.713,
            170.625,
            246.32,
            167.887,
            248.788,
            165.297,
            251.128,
            162.843,
            253.35,
            160.516,
            255.462,
            158.304,
            257.474,
            156.201,
            259.392,
            154.198,
            261.223,
            152.288,
            262.973,
            150.464,
            264.647,
            148.722,
            266.251,
            147.056,
            267.789,
            145.46,
            269.266,
            143.931,
            270.684,
            142.465,
            272.049,
            141.057,
            273.362,
            139.704,
            274.627,
            138.404,
            275.847,
            137.152,
            277.024,
            135.947,
            278.161,
            134.786,
            279.26,
            133.666,
            280.322,
            132.585,
            281.35,
            131.542,
            282.345,
            130.534,
            283.31,
            129.56,
            284.245,
            128.618,
            285.152,
            127.706,
            286.032,
            126.823,
            286.888,
            125.967,
            287.719,
            125.138,
            288.527,
            124.334,
            289.312,
            123.554,
            290.077,
            122.797,
            290.822,
            122.062,
            291.547,
            121.348,
            292.254,
            120.654,
            292.943,
            119.98,
            293.614,
            119.323,
            294.268,
            118.685,
            294.907,
            118.064,
            295.529,
            117.459,
            296.137,
            116.869,
            296.73,
            116.295,
            297.308,
            115.735,
            297.873,
            115.19,
            298.425,
            114.657,
            298.963,
            114.138,
            299.489,
            113.632,
            300.003,
            113.137,
            300.505,
            112.654,
            300.995,
            112.182,
            301.043,
            112.136
          ],
          [
            469.258,
            289.075,
            461.455,
            276.228,
            454.522,
            264.816,
            448.318,
            254.613,
            442.731,
            245.436,
            437.669,
            237.137,
            433.06,
            229.597,
            428.84,
            222.716,
            424.96,
            216.41,
            421.377,
            210.612,
            418.054,
            205.261,
            414.961,
            200.308,
            412.071,
            195.711,
            409.361,
            191.431,
            406.812,
            187.438,
            404.407,
            183.704,
            402.13,
            180.204,
            399.969,
            176.917,
            397.912,
            173.823,
            395.95,
            170.907,
            394.078,
            168.154,
            392.29,
            165.55,
            390.582,
            163.083,
            388.951,
            160.743,
            387.392,
            158.52,
            385.902,
            156.407,
            384.478,
            154.394,
            383.118,
            152.475,
            381.819,
            150.643,
            380.579,
            148.893,
            379.396,
            147.219,
            378.268,
            145.617,
            377.193,
            144.081,
            376.17,
            142.609,
            375.197,
            141.195,
            374.273,
            139.837,
            373.397,
            138.532,
            372.564,
            137.275,
            371.773,
            136.066,
            371.018,
            134.9,
            370.298,
            133.776,
            369.609,
            132.692,
            368.948,
            131.645,
            368.314,
            130.633,
            367.703,
            129.656,
            367.114,
            128.71,
            366.544,
            127.795,
            365.992,
            126.91,
            365.456,
            126.052,
            364.933,
            125.22,
            364.423,
            124.413,
            363.925,
            123.631,
            363.435,
            122.872,
            362.954,
            122.135,
            362.481,
            121.419,
            362.015,
            120.723,
            361.557,
            120.046,
            361.107,
            119.388,
            360.664,
            118.748,
            360.228,
            118.125,
            359.801,
            117.518,
            359.381,
            116.927,
            358.969,
            116.352,
            358.565,
            115.791,
            358.169,
            115.244,
            357.78,
            114.71,
            357.399,
            114.19,
            357.027,
            113.682,
            356.662,
            113.186,
            356.305,
            112.702,
            355.956,
            112.229,
            355.887,
            112.136
          ],
          [
            574.151,
            234.036,
            566.652,
            226.77,
            559.786,
            220.128,
            553.466,
            214.033,
            547.616,
            208.421,
            542.175,
            203.235,
            537.088,
            198.429,
            532.31,
            193.963,
            527.799,
            189.801,
            523.523,
            185.915,
            519.45,
            182.277,
            515.554,
            178.865,
            511.812,
            175.657,
            508.203,
            172.636,
            504.709,
            169.787,
            501.314,
            167.095,
            498.004,
            164.547,
            494.767,
            162.132,
            491.6,
            159.84,
            488.505,
            157.662,
            485.483,
            155.59,
            482.538,
            153.615,
            479.668,
            151.732,
            476.876,
            149.933,
            474.163,
            148.215,
            471.529,
            146.57,
            468.976,
            144.995,
            466.504,
            143.485,
            464.115,
            142.037,
            461.808,
            140.646,
            459.584,
            139.309,
            457.445,
            138.023,
            455.39,
            136.786,
            453.42,
            135.594,
            451.531,
            134.446,
            449.716,
            133.338,
            447.969,
            132.269,
            446.284,
            131.236,
            444.656,
            130.238,
            443.08,
            129.274,
            441.55,
            128.341,
            440.063,
            127.438,
            438.615,
            126.563,
            437.201,
            125.716,
            435.817,
            124.894,
            434.461,
            124.098,
            433.129,
            123.325,
            431.818,
            122.574,
            430.526,
            121.846,
            429.248,
            121.138,
            427.986,
            120.45,
            426.738,
            119.781,
            425.505,
            119.13,
            424.289,
            118.497,
            423.091,
            117.88,
            421.909,
            117.28,
            420.746,
            116.695,
            419.602,
            116.126,
            418.477,
            115.57,
            417.372,
            115.029,
            416.287,
            114.5,
            415.222,
            113.985,
            414.179,
            113.482,
            413.157,
            112.991,
            412.157,
            112.511,
            411.374,
            112.136
          ]
        ],
        "curves_with_geometry": 5,
        "valid_curves_before_separation": 5,
        "strict_valid_curves_before_separation": 5,
        "pairs_evaluated": 10,
        "pairs_meeting_separation": 10,
        "strict_pairs_evaluated": 10,
        "strict_pairs_meeting_separation": 10,
        "strict_valid_lane_lines": 5,
        "length_check": {
          "min_length_m": 180.0,
          "pass_count": 5,
          "total_count": 5,
          "pass_rate": 1.0,
          "stats_m": {
            "count": 5,
            "min": 486.11809329485754,
            "median": 702.0139331743288,
            "max": 731.4391037822257
          }
        },
        "curvature_check": {
          "max_curvature_1pm": 0.1,
          "soft_max_curvature_1pm": 0.18000000000000002,
          "pass_count": 5,
          "soft_pass_count": 5,
          "total_count": 5,
          "pass_rate": 1.0,
          "soft_pass_rate": 1.0,
          "stats_1pm": {
            "count": 5,
            "min": 1.3006788053584359e-05,
            "median": 5.6682363979323905e-05,
            "max": 0.00018239316094984678
          }
        },
        "separation_check": {
          "min_separation_m": 2.5,
          "pairs_meeting_separation": 10,
          "pairs_evaluated": 10,
          "pass_rate": 1.0,
          "stats_m": {
            "count": 10,
            "min": 45.34163148532403,
            "median": 131.31605856797614,
            "max": 298.2262975730348
          }
        },
        "strict_separation_check": {
          "min_separation_m": 2.5,
          "pairs_meeting_separation": 10,
          "pairs_evaluated": 10,
          "pass_rate": 1.0,
          "stats_m": {
            "count": 10,
            "min": 45.34163148532403,
            "median": 131.31605856797614,
            "max": 298.2262975730348
          }
        },
        "curves_total": 5
      }
    },
    "gps": {
      "score": 1.0,
      "er": 1.6027250677300515,
      "lat_stdev": 1.3605380058288574,
      "lon_stdev": 0.8471505045890808
    },
    "connectivity": {
      "score": 0.9375,
      "subscores": {
        "avg_d_mbps": 1.0,
        "avg_u_mbps": 1.0,
        "avg_download_latency_ms": 0.75,
        "avg_upload_latency_ms": 1.0
      },
      "metrics": {
        "avg_d_mbps": 1131.543,
        "avg_u_mbps": 63.554,
        "avg_download_latency_ms": 17.0,
        "avg_upload_latency_ms": 17.0
      }
    },
    "weights": {
      "w1": 0.6,
      "w2": 0.4,
      "k1": 1.0,
      "k2": 0.0,
      "k3": 0.0,
      "m1": 0.5,
      "m2": 0.4,
      "m3": 0.1
    },
    "overall_score": 0.9415,
    "overall_score_details": {
      "formula": "overall_score = w1*physical_score + w2*digital_score",
      "physical_contribution": {
        "weight": 0.6,
        "score": 0.99,
        "weighted_score": 0.594
      },
      "digital_contribution": {
        "weight": 0.4,
        "score": 0.86875,
        "weighted_score": 0.34750000000000003
      },
      "components": {
        "physical_infra_score": 0.594,
        "digital_infra_score": 0.34750000000000003,
        "physical_score": 0.99,
        "digital_score": 0.86875,
        "lane_score": 0.99,
        "pavement_score": 0.0,
        "traffic_sign_score": 0.0,
        "hd_maps_score": 0.0,
        "connectivity_score": 0.9375,
        "gps_score": 1.0
      }
    }
  }
}