{
  "image": "image_88010.jpg",
  "frame_index": 88010,
  "timestamp_ns": 1749051876464164719,
  "gps": {
    "timestamp_ns": 1749051876459032563,
    "lat": 36.161614011460514,
    "lon": -79.7881841241009,
    "hgt": 222.685600717552,
    "lat_stdev": 1.6025662422180176,
    "lon_stdev": 1.2020732164382935,
    "hgt_stdev": 4.015707969665527,
    "num_svs": 8,
    "num_sol_svs": 5,
    "hdop": null,
    "vdop": null,
    "undulation": -32.70000076293945,
    "diff_age": 5.0,
    "sol_age": 0.0
  },
  "connectivity": {
    "avg_d_mbps": 5.427,
    "avg_u_mbps": 4.509,
    "avg_latency_ms": 30.0,
    "avg_download_latency_ms": 30.0,
    "avg_upload_latency_ms": 30.0,
    "tests": 1,
    "source": "nearest"
  },
  "connectivity_error": null,
  "lane": {
    "image": "image_88010.jpg",
    "results": [
      {
        "thr": "0.25",
        "curves": [
          [
            -9.81851,
            234.036,
            4.9143,
            226.77,
            18.3929,
            220.128,
            30.7828,
            214.033,
            42.2232,
            208.421,
            52.8324,
            203.235,
            62.7111,
            198.429,
            71.9457,
            193.963,
            80.6111,
            189.801,
            88.7722,
            185.915,
            96.4821,
            182.277,
            103.775,
            178.865,
            110.678,
            175.657,
            117.214,
            172.636,
            123.406,
            169.787,
            129.271,
            167.095,
            134.826,
            164.547,
            140.086,
            162.132,
            145.066,
            159.84,
            149.778,
            157.662,
            154.24,
            155.59,
            158.471,
            153.615,
            162.487,
            151.732,
            166.302,
            149.933,
            169.931,
            148.215,
            173.385,
            146.57,
            176.676,
            144.995,
            179.814,
            143.485,
            182.808,
            142.037,
            185.67,
            140.646,
            188.408,
            139.309,
            191.031,
            138.023,
            193.547,
            136.786,
            195.965,
            135.594,
            198.289,
            134.446,
            200.529,
            133.338,
            202.688,
            132.269,
            202.688,
            132.269
          ],
          [
            99.5512,
            374.81,
            118.07,
            350.376,
            133.823,
            329.591,
            147.385,
            311.695,
            159.183,
            296.125,
            169.539,
            282.455,
            178.702,
            270.358,
            186.866,
            259.576,
            194.186,
            249.906,
            200.784,
            241.185,
            206.763,
            233.279,
            212.204,
            226.079,
            217.176,
            219.495,
            221.737,
            213.451,
            225.935,
            207.884,
            229.811,
            202.738,
            233.4,
            197.967,
            236.732,
            193.533,
            239.833,
            189.401,
            242.725,
            185.541,
            245.43,
            181.926,
            247.963,
            178.535,
            250.342,
            175.347,
            252.58,
            172.344,
            254.69,
            169.511,
            256.682,
            166.834,
            258.568,
            164.3,
            260.354,
            161.898,
            262.05,
            159.618,
            263.662,
            157.45,
            265.197,
            155.388,
            266.661,
            153.423,
            268.06,
            151.548,
            269.397,
            149.758,
            270.677,
            148.047,
            271.905,
            146.409,
            273.083,
            144.841,
            274.216,
            143.338,
            275.307,
            141.895,
            276.357,
            140.51,
            277.369,
            139.178,
            278.344,
            137.897,
            279.283,
            136.665,
            280.189,
            135.477,
            281.061,
            134.333,
            281.902,
            133.229,
            282.712,
            132.164,
            283.493,
            131.135,
            284.245,
            130.141,
            284.97,
            129.179,
            285.668,
            128.249,
            286.339,
            127.349,
            286.986,
            126.477,
            287.607,
            125.632,
            288.205,
            124.814,
            288.779,
            124.019,
            289.33,
            123.249,
            289.859,
            122.501,
            290.367,
            121.774,
            290.855,
            121.068,
            291.325,
            120.382,
            291.777,
            119.715,
            292.212,
            119.066,
            292.632,
            118.434,
            293.037,
            117.82,
            293.428,
            117.221,
            293.807,
            116.638,
            294.173,
            116.069,
            294.528,
            115.515,
            294.872,
            114.975,
            295.206,
            114.448,
            295.53,
            113.934,
            295.846,
            113.432,
            296.154,
            112.942,
            296.454,
            112.464,
            296.659,
            112.136
          ],
          [
            543.282,
            374.81,
            526.02,
            350.376,
            511.334,
            329.591,
            498.686,
            311.695,
            487.676,
            296.125,
            478.003,
            282.455,
            469.435,
            270.358,
            461.79,
            259.576,
            454.924,
            249.906,
            448.721,
            241.185,
            443.086,
            233.279,
            437.943,
            226.079,
            433.226,
            219.495,
            428.883,
            213.451,
            424.869,
            207.884,
            421.144,
            202.738,
            417.677,
            197.967,
            414.438,
            193.533,
            411.404,
            189.401,
            408.554,
            185.541,
            405.87,
            181.926,
            403.338,
            178.535,
            400.945,
            175.347,
            398.682,
            172.344,
            396.538,
            169.511,
            394.504,
            166.834,
            392.573,
            164.3,
            390.738,
            161.898,
            388.993,
            159.618,
            387.332,
            157.45,
            385.751,
            155.388,
            384.245,
            153.423,
            382.809,
            151.548,
            381.44,
            149.758,
            380.134,
            148.047,
            378.889,
            146.409,
            377.701,
            144.841,
            376.568,
            143.338,
            375.488,
            141.895,
            374.456,
            140.51,
            373.471,
            139.178,
            372.527,
            137.897,
            371.623,
            136.665,
            370.755,
            135.477,
            369.921,
            134.333,
            369.119,
            133.229,
            368.345,
            132.164,
            367.599,
            131.135,
            366.877,
            130.141,
            366.179,
            129.179,
            365.502,
            128.249,
            364.845,
            127.349,
            364.206,
            126.477,
            363.585,
            125.632,
            362.979,
            124.814,
            362.387,
            124.019,
            361.809,
            123.249,
            361.243,
            122.501,
            360.688,
            121.774,
            360.145,
            121.068,
            359.614,
            120.382,
            359.094,
            119.715,
            358.584,
            119.066,
            358.085,
            118.434,
            357.597,
            117.82,
            357.119,
            117.221,
            356.651,
            116.638,
            356.193,
            116.069,
            355.745,
            115.515,
            355.307,
            114.975,
            354.878,
            114.448,
            354.458,
            113.934,
            354.048,
            113.432,
            353.647,
            112.942,
            353.255,
            112.464,
            352.986,
            112.136
          ]
        ]
      },
      {
        "thr": "0.3",
        "curves": [
          [
            -9.82078,
            234.036,
            4.91449,
            226.77,
            18.3951,
            220.128,
            30.7864,
            214.033,
            42.2277,
            208.421,
            52.8368,
            203.235,
            62.7144,
            198.429,
            71.9471,
            193.963,
            80.6095,
            189.801,
            88.7664,
            185.915,
            96.4712,
            182.277,
            103.759,
            178.865,
            110.658,
            175.657,
            117.194,
            172.636,
            123.387,
            169.787,
            129.258,
            167.095,
            134.825,
            164.547,
            140.102,
            162.132,
            145.104,
            159.84,
            149.845,
            157.662,
            154.34,
            155.59,
            158.605,
            153.615,
            162.653,
            151.732,
            166.497,
            149.933,
            170.149,
            148.215,
            173.62,
            146.57,
            176.918,
            144.995,
            180.053,
            143.485,
            183.033,
            142.037,
            185.87,
            140.646,
            188.576,
            139.309,
            191.16,
            138.023,
            193.633,
            136.786,
            196.004,
            135.594,
            198.28,
            134.446,
            200.47,
            133.338,
            202.581,
            132.269,
            202.581,
            132.269
          ],
          [
            99.5122,
            374.81,
            118.044,
            350.376,
            133.806,
            329.591,
            147.377,
            311.695,
            159.182,
            296.125,
            169.544,
            282.455,
            178.713,
            270.358,
            186.881,
            259.576,
            194.204,
            249.906,
            200.805,
            241.185,
            206.785,
            233.279,
            212.228,
            226.079,
            217.201,
            219.495,
            221.762,
            213.451,
            225.959,
            207.884,
            229.834,
            202.738,
            233.422,
            197.967,
            236.752,
            193.533,
            239.85,
            189.401,
            242.74,
            185.541,
            245.44,
            181.926,
            247.97,
            178.535,
            250.344,
            175.347,
            252.578,
            172.344,
            254.683,
            169.511,
            256.67,
            166.834,
            258.55,
            164.3,
            260.331,
            161.898,
            262.02,
            159.618,
            263.626,
            157.45,
            265.155,
            155.388,
            266.613,
            153.423,
            268.004,
            151.548,
            269.334,
            149.758,
            270.607,
            148.047,
            271.828,
            146.409,
            272.999,
            144.841,
            274.125,
            143.338,
            275.208,
            141.895,
            276.25,
            140.51,
            277.255,
            139.178,
            278.222,
            137.897,
            279.155,
            136.665,
            280.054,
            135.477,
            280.921,
            134.333,
            281.757,
            133.229,
            282.564,
            132.164,
            283.342,
            131.135,
            284.092,
            130.141,
            284.816,
            129.179,
            285.514,
            128.249,
            286.188,
            127.349,
            286.837,
            126.477,
            287.463,
            125.632,
            288.067,
            124.814,
            288.649,
            124.019,
            289.21,
            123.249,
            289.75,
            122.501,
            290.27,
            121.774,
            290.772,
            121.068,
            291.257,
            120.382,
            291.725,
            119.715,
            292.177,
            119.066,
            292.614,
            118.434,
            293.038,
            117.82,
            293.448,
            117.221,
            293.845,
            116.638,
            294.231,
            116.069,
            294.606,
            115.515,
            294.969,
            114.975,
            295.323,
            114.448,
            295.667,
            113.934,
            296.003,
            113.432,
            296.33,
            112.942,
            296.649,
            112.464,
            296.867,
            112.136
          ],
          [
            543.445,
            374.81,
            526.133,
            350.376,
            511.405,
            329.591,
            498.721,
            311.695,
            487.681,
            296.125,
            477.983,
            282.455,
            469.394,
            270.358,
            461.731,
            259.576,
            454.851,
            249.906,
            448.637,
            241.185,
            442.994,
            233.279,
            437.846,
            226.079,
            433.127,
            219.495,
            428.783,
            213.451,
            424.771,
            207.884,
            421.05,
            202.738,
            417.589,
            197.967,
            414.359,
            193.533,
            411.336,
            189.401,
            408.498,
            185.541,
            405.828,
            181.926,
            403.311,
            178.535,
            400.935,
            175.347,
            398.687,
            172.344,
            396.559,
            169.511,
            394.54,
            166.834,
            392.623,
            164.3,
            390.802,
            161.898,
            389.068,
            159.618,
            387.418,
            157.45,
            385.844,
            155.388,
            384.344,
            153.423,
            382.911,
            151.548,
            381.544,
            149.758,
            380.237,
            148.047,
            378.987,
            146.409,
            377.793,
            144.841,
            376.65,
            143.338,
            375.556,
            141.895,
            374.509,
            140.51,
            373.506,
            139.178,
            372.543,
            137.897,
            371.619,
            136.665,
            370.731,
            135.477,
            369.877,
            134.333,
            369.055,
            133.229,
            368.262,
            132.164,
            367.498,
            131.135,
            366.761,
            130.141,
            366.049,
            129.179,
            365.36,
            128.249,
            364.694,
            127.349,
            364.05,
            126.477,
            363.425,
            125.632,
            362.819,
            124.814,
            362.231,
            124.019,
            361.66,
            123.249,
            361.105,
            122.501,
            360.566,
            121.774,
            360.041,
            121.068,
            359.531,
            120.382,
            359.034,
            119.715,
            358.55,
            119.066,
            358.079,
            118.434,
            357.619,
            117.82,
            357.172,
            117.221,
            356.736,
            116.638,
            356.311,
            116.069,
            355.896,
            115.515,
            355.491,
            114.975,
            355.096,
            114.448,
            354.711,
            113.934,
            354.334,
            113.432,
            353.967,
            112.942,
            353.608,
            112.464,
            353.362,
            112.136
          ]
        ]
      },
      {
        "thr": "0.4",
        "curves": [
          [
            -9.61067,
            234.036,
            5.02278,
            226.77,
            18.4141,
            220.128,
            30.7305,
            214.033,
            42.1131,
            208.421,
            52.6812,
            203.235,
            62.5367,
            198.429,
            71.7672,
            193.963,
            80.4483,
            189.801,
            88.6455,
            185.915,
            96.4115,
            182.277,
            103.774,
            178.865,
            110.754,
            175.657,
            117.369,
            172.636,
            123.636,
            169.787,
            129.568,
            167.095,
            135.177,
            164.547,
            140.477,
            162.132,
            145.475,
            159.84,
            150.186,
            157.662,
            154.629,
            155.59,
            158.827,
            153.615,
            162.801,
            151.732,
            166.567,
            149.933,
            170.143,
            148.215,
            173.544,
            146.57,
            176.783,
            144.995,
            179.874,
            143.485,
            182.827,
            142.037,
            185.653,
            140.646,
            188.36,
            139.309,
            190.957,
            138.023,
            193.449,
            136.786,
            195.846,
            135.594,
            198.152,
            134.446,
            200.374,
            133.338,
            202.518,
            132.269,
            202.518,
            132.269
          ],
          [
            99.6465,
            374.81,
            118.166,
            350.376,
            133.918,
            329.591,
            147.48,
            311.695,
            159.278,
            296.125,
            169.634,
            282.455,
            178.797,
            270.358,
            186.96,
            259.576,
            194.279,
            249.906,
            200.877,
            241.185,
            206.854,
            233.279,
            212.293,
            226.079,
            217.264,
            219.495,
            221.823,
            213.451,
            226.019,
            207.884,
            229.892,
            202.738,
            233.479,
            197.967,
            236.808,
            193.533,
            239.905,
            189.401,
            242.795,
            185.541,
            245.495,
            181.926,
            248.025,
            178.535,
            250.4,
            175.347,
            252.634,
            172.344,
            254.74,
            169.511,
            256.729,
            166.834,
            258.611,
            164.3,
            260.394,
            161.898,
            262.087,
            159.618,
            263.697,
            157.45,
            265.23,
            155.388,
            266.692,
            153.423,
            268.088,
            151.548,
            269.424,
            149.758,
            270.704,
            148.047,
            271.931,
            146.409,
            273.11,
            144.841,
            274.243,
            143.338,
            275.335,
            141.895,
            276.387,
            140.51,
            277.4,
            139.178,
            278.377,
            137.897,
            279.319,
            136.665,
            280.227,
            135.477,
            281.103,
            134.333,
            281.947,
            133.229,
            282.76,
            132.164,
            283.545,
            131.135,
            284.3,
            130.141,
            285.028,
            129.179,
            285.73,
            128.249,
            286.405,
            127.349,
            287.055,
            126.477,
            287.68,
            125.632,
            288.281,
            124.814,
            288.859,
            124.019,
            289.414,
            123.249,
            289.946,
            122.501,
            290.457,
            121.774,
            290.949,
            121.068,
            291.422,
            120.382,
            291.876,
            119.715,
            292.315,
            119.066,
            292.738,
            118.434,
            293.145,
            117.82,
            293.54,
            117.221,
            293.921,
            116.638,
            294.289,
            116.069,
            294.647,
            115.515,
            294.993,
            114.975,
            295.33,
            114.448,
            295.657,
            113.934,
            295.975,
            113.432,
            296.285,
            112.942,
            296.587,
            112.464,
            296.794,
            112.136
          ],
          [
            543.987,
            374.81,
            526.631,
            350.376,
            511.867,
            329.591,
            499.152,
            311.695,
            488.085,
            296.125,
            478.362,
            282.455,
            469.752,
            270.358,
            462.071,
            259.576,
            455.174,
            249.906,
            448.945,
            241.185,
            443.289,
            233.279,
            438.129,
            226.079,
            433.399,
            219.495,
            429.046,
            213.451,
            425.025,
            207.884,
            421.296,
            202.738,
            417.828,
            197.967,
            414.591,
            193.533,
            411.562,
            189.401,
            408.719,
            185.541,
            406.045,
            181.926,
            403.523,
            178.535,
            401.143,
            175.347,
            398.891,
            172.344,
            396.758,
            169.511,
            394.735,
            166.834,
            392.814,
            164.3,
            390.988,
            161.898,
            389.249,
            159.618,
            387.592,
            157.45,
            386.013,
            155.388,
            384.505,
            153.423,
            383.066,
            151.548,
            381.69,
            149.758,
            380.374,
            148.047,
            379.115,
            146.409,
            377.91,
            144.841,
            376.756,
            143.338,
            375.651,
            141.895,
            374.591,
            140.51,
            373.574,
            139.178,
            372.598,
            137.897,
            371.66,
            136.665,
            370.758,
            135.477,
            369.89,
            134.333,
            369.054,
            133.229,
            368.249,
            132.164,
            367.472,
            131.135,
            366.722,
            130.141,
            365.998,
            129.179,
            365.299,
            128.249,
            364.623,
            127.349,
            363.969,
            126.477,
            363.336,
            125.632,
            362.723,
            124.814,
            362.129,
            124.019,
            361.553,
            123.249,
            360.994,
            122.501,
            360.452,
            121.774,
            359.925,
            121.068,
            359.414,
            120.382,
            358.917,
            119.715,
            358.433,
            119.066,
            357.963,
            118.434,
            357.506,
            117.82,
            357.061,
            117.221,
            356.628,
            116.638,
            356.205,
            116.069,
            355.794,
            115.515,
            355.393,
            114.975,
            355.002,
            114.448,
            354.62,
            113.934,
            354.248,
            113.432,
            353.885,
            112.942,
            353.53,
            112.464,
            353.286,
            112.136
          ]
        ]
      }
    ]
  }
}