{
  "image": "image_35440.jpg",
  "frame_index": 35440,
  "timestamp_ns": 1749050138053377792,
  "gps": {
    "timestamp_ns": 1749050137959814729,
    "lat": 36.31868502881557,
    "lon": -79.78829549124174,
    "hgt": 270.8273327536881,
    "lat_stdev": 1.6329634189605713,
    "lon_stdev": 0.9327157139778137,
    "hgt_stdev": 2.949130058288574,
    "num_svs": 19,
    "num_sol_svs": 8,
    "hdop": null,
    "vdop": null,
    "undulation": -33.0,
    "diff_age": 4.0,
    "sol_age": 0.0
  },
  "connectivity": {
    "avg_d_mbps": 165.433,
    "avg_u_mbps": 86.847,
    "avg_latency_ms": 33.0,
    "avg_download_latency_ms": 33.0,
    "avg_upload_latency_ms": 33.0,
    "tests": 6,
    "source": "nearest"
  },
  "connectivity_error": null,
  "lane": {
    "image": "image_35440.jpg",
    "results": [
      {
        "thr": "0.25",
        "curves": [
          [
            -7.02605,
            248.994,
            11.3711,
            240.359,
            28.0593,
            232.529,
            43.2697,
            225.395,
            57.194,
            218.868,
            69.9926,
            212.874,
            81.8008,
            207.351,
            92.7335,
            202.244,
            102.889,
            197.509,
            112.351,
            193.107,
            121.192,
            189.003,
            129.477,
            185.168,
            137.261,
            181.577,
            144.591,
            178.207,
            151.511,
            175.038,
            158.058,
            172.053,
            164.266,
            169.237,
            170.165,
            166.574,
            175.78,
            164.054,
            181.135,
            161.664,
            186.249,
            159.396,
            191.141,
            157.24,
            195.827,
            155.187,
            200.323,
            153.231,
            204.642,
            151.365,
            208.795,
            149.584,
            212.795,
            147.88,
            216.652,
            146.25,
            220.375,
            144.688,
            223.973,
            143.191,
            227.454,
            141.754,
            230.824,
            140.374,
            234.092,
            139.048,
            237.262,
            137.772,
            240.341,
            136.544,
            243.333,
            135.361,
            246.241,
            134.221,
            249.068,
            133.121,
            251.816,
            132.059,
            254.488,
            131.034,
            257.087,
            130.043,
            259.614,
            129.085,
            262.071,
            128.158,
            264.461,
            127.261,
            266.786,
            126.392,
            269.046,
            125.549,
            271.244,
            124.733,
            273.381,
            123.941,
            275.458,
            123.173,
            277.478,
            122.427,
            279.44,
            121.703,
            281.346,
            120.999,
            283.199,
            120.315,
            285.001,
            119.649,
            286.753,
            119.002,
            288.459,
            118.372,
            290.119,
            117.759,
            291.736,
            117.162,
            293.311,
            116.58,
            294.845,
            116.013,
            296.341,
            115.461,
            297.8,
            114.922,
            299.223,
            114.396,
            300.612,
            113.883,
            301.967,
            113.383,
            303.29,
            112.894,
            304.582,
            112.417,
            305.343,
            112.136
          ],
          [
            112.159,
            374.81,
            131.778,
            350.376,
            148.474,
            329.591,
            162.861,
            311.695,
            175.396,
            296.125,
            186.424,
            282.455,
            196.209,
            270.358,
            204.958,
            259.576,
            212.838,
            249.906,
            219.98,
            241.185,
            226.492,
            233.279,
            232.463,
            226.079,
            237.965,
            219.495,
            243.06,
            213.451,
            247.8,
            207.884,
            252.228,
            202.738,
            256.382,
            197.967,
            260.294,
            193.533,
            263.991,
            189.401,
            267.498,
            185.541,
            270.835,
            181.926,
            274.014,
            178.535,
            277.047,
            175.347,
            279.945,
            172.344,
            282.718,
            169.511,
            285.373,
            166.834,
            287.919,
            164.3,
            290.361,
            161.898,
            292.705,
            159.618,
            294.957,
            157.45,
            297.123,
            155.388,
            299.205,
            153.423,
            301.208,
            151.548,
            303.137,
            149.758,
            304.993,
            148.047,
            306.78,
            146.409,
            308.501,
            144.841,
            310.159,
            143.338,
            311.756,
            141.895,
            313.295,
            140.51,
            314.781,
            139.178,
            316.218,
            137.897,
            317.61,
            136.665,
            318.961,
            135.477,
            320.273,
            134.333,
            321.55,
            133.229,
            322.795,
            132.164,
            324.01,
            131.135,
            325.198,
            130.141,
            326.36,
            129.179,
            327.5,
            128.249,
            328.619,
            127.349,
            329.719,
            126.477,
            330.802,
            125.632,
            331.87,
            124.814,
            332.923,
            124.019,
            333.964,
            123.249,
            334.993,
            122.501,
            336.011,
            121.774,
            337.017,
            121.068,
            338.01,
            120.382,
            338.99,
            119.715,
            339.956,
            119.066,
            340.909,
            118.434,
            341.847,
            117.82,
            342.771,
            117.221,
            343.679,
            116.638,
            344.573,
            116.069,
            345.45,
            115.515,
            346.312,
            114.975,
            347.158,
            114.448,
            347.987,
            113.934,
            348.799,
            113.432,
            349.594,
            112.942,
            350.372,
            112.464,
            350.906,
            112.136
          ],
          [
            506.788,
            374.81,
            493.732,
            350.376,
            482.632,
            329.591,
            473.085,
            311.695,
            464.792,
            296.125,
            457.53,
            282.455,
            451.124,
            270.358,
            445.439,
            259.576,
            440.366,
            249.906,
            435.82,
            241.185,
            431.73,
            233.279,
            428.038,
            226.079,
            424.696,
            219.495,
            421.664,
            213.451,
            418.908,
            207.884,
            416.401,
            202.738,
            414.116,
            197.967,
            412.034,
            193.533,
            410.136,
            189.401,
            408.406,
            185.541,
            406.83,
            181.926,
            405.393,
            178.535,
            404.082,
            175.347,
            402.887,
            172.344,
            401.796,
            169.511,
            400.801,
            166.834,
            399.894,
            164.3,
            399.068,
            161.898,
            398.316,
            159.618,
            397.633,
            157.45,
            397.013,
            155.388,
            396.451,
            153.423,
            395.944,
            151.548,
            395.488,
            149.758,
            395.078,
            148.047,
            394.711,
            146.409,
            394.385,
            144.841,
            394.097,
            143.338,
            393.844,
            141.895,
            393.625,
            140.51,
            393.436,
            139.178,
            393.278,
            137.897,
            393.148,
            136.665,
            393.044,
            135.477,
            392.967,
            134.333,
            392.913,
            133.229,
            392.883,
            132.164,
            392.876,
            131.135,
            392.889,
            130.141,
            392.923,
            129.179,
            392.976,
            128.249,
            393.048,
            127.349,
            393.138,
            126.477,
            393.245,
            125.632,
            393.369,
            124.814,
            393.509,
            124.019,
            393.664,
            123.249,
            393.834,
            122.501,
            394.017,
            121.774,
            394.212,
            121.068,
            394.416,
            120.382,
            394.63,
            119.715,
            394.851,
            119.066,
            395.078,
            118.434,
            395.311,
            117.82,
            395.547,
            117.221,
            395.786,
            116.638,
            396.026,
            116.069,
            396.268,
            115.515,
            396.509,
            114.975,
            396.75,
            114.448,
            396.988,
            113.934,
            397.224,
            113.432,
            397.457,
            112.942,
            397.686,
            112.464,
            397.843,
            112.136
          ]
        ]
      },
      {
        "thr": "0.3",
        "curves": [
          [
            -7.00052,
            248.994,
            11.3807,
            240.359,
            28.0549,
            232.529,
            43.2534,
            225.395,
            57.1679,
            218.868,
            69.959,
            212.874,
            81.7622,
            207.351,
            92.6922,
            202.244,
            102.847,
            197.509,
            112.312,
            193.107,
            121.159,
            189.003,
            129.451,
            185.168,
            137.245,
            181.577,
            144.589,
            178.207,
            151.524,
            175.038,
            158.09,
            172.053,
            164.32,
            169.237,
            170.243,
            166.574,
            175.885,
            164.054,
            181.268,
            161.664,
            186.412,
            159.396,
            191.333,
            157.24,
            196.047,
            155.187,
            200.569,
            153.231,
            204.912,
            151.365,
            209.088,
            149.584,
            213.107,
            147.88,
            216.979,
            146.25,
            220.714,
            144.688,
            224.319,
            143.191,
            227.802,
            141.754,
            231.17,
            140.374,
            234.43,
            139.048,
            237.588,
            137.772,
            240.648,
            136.544,
            243.617,
            135.361,
            246.497,
            134.221,
            249.293,
            133.121,
            252.008,
            132.059,
            254.645,
            131.034,
            257.208,
            130.043,
            259.7,
            129.085,
            262.123,
            128.158,
            264.479,
            127.261,
            266.772,
            126.392,
            269.003,
            125.549,
            271.174,
            124.733,
            273.288,
            123.941,
            275.345,
            123.173,
            277.349,
            122.427,
            279.3,
            121.703,
            281.201,
            120.999,
            283.052,
            120.315,
            284.856,
            119.649,
            286.615,
            119.002,
            288.329,
            118.372,
            290.001,
            117.759,
            291.632,
            117.162,
            293.223,
            116.58,
            294.776,
            116.013,
            296.292,
            115.461,
            297.771,
            114.922,
            299.215,
            114.396,
            300.626,
            113.883,
            302.003,
            113.383,
            303.348,
            112.894,
            304.663,
            112.417,
            305.437,
            112.136
          ],
          [
            111.959,
            374.81,
            131.645,
            350.376,
            148.396,
            329.591,
            162.83,
            311.695,
            175.405,
            296.125,
            186.464,
            282.455,
            196.275,
            270.358,
            205.046,
            259.576,
            212.942,
            249.906,
            220.094,
            241.185,
            226.613,
            233.279,
            232.585,
            226.079,
            238.085,
            219.495,
            243.175,
            213.451,
            247.905,
            207.884,
            252.32,
            202.738,
            256.457,
            197.967,
            260.348,
            193.533,
            264.022,
            189.401,
            267.503,
            185.541,
            270.809,
            181.926,
            273.956,
            178.535,
            276.957,
            175.347,
            279.822,
            172.344,
            282.562,
            169.511,
            285.186,
            166.834,
            287.701,
            164.3,
            290.115,
            161.898,
            292.433,
            159.618,
            294.663,
            157.45,
            296.809,
            155.388,
            298.875,
            153.423,
            300.866,
            151.548,
            302.786,
            149.758,
            304.639,
            148.047,
            306.427,
            146.409,
            308.154,
            144.841,
            309.822,
            143.338,
            311.434,
            141.895,
            312.993,
            140.51,
            314.503,
            139.178,
            315.967,
            137.897,
            317.388,
            136.665,
            318.769,
            135.477,
            320.113,
            134.333,
            321.422,
            133.229,
            322.698,
            132.164,
            323.944,
            131.135,
            325.161,
            130.141,
            326.352,
            129.179,
            327.518,
            128.249,
            328.66,
            127.349,
            329.781,
            126.477,
            330.881,
            125.632,
            331.962,
            124.814,
            333.025,
            124.019,
            334.072,
            123.249,
            335.103,
            122.501,
            336.118,
            121.774,
            337.118,
            121.068,
            338.102,
            120.382,
            339.07,
            119.715,
            340.022,
            119.066,
            340.957,
            118.434,
            341.877,
            117.82,
            342.78,
            117.221,
            343.667,
            116.638,
            344.537,
            116.069,
            345.391,
            115.515,
            346.228,
            114.975,
            347.048,
            114.448,
            347.852,
            113.934,
            348.639,
            113.432,
            349.409,
            112.942,
            350.162,
            112.464,
            350.679,
            112.136
          ],
          [
            506.802,
            374.81,
            493.687,
            350.376,
            482.536,
            329.591,
            472.946,
            311.695,
            464.617,
            296.125,
            457.324,
            282.455,
            450.892,
            270.358,
            445.186,
            259.576,
            440.096,
            249.906,
            435.536,
            241.185,
            431.435,
            233.279,
            427.736,
            226.079,
            424.389,
            219.495,
            421.356,
            213.451,
            418.602,
            207.884,
            416.097,
            202.738,
            413.819,
            197.967,
            411.745,
            193.533,
            409.857,
            189.401,
            408.14,
            185.541,
            406.579,
            181.926,
            405.158,
            178.535,
            403.864,
            175.347,
            402.686,
            172.344,
            401.613,
            169.511,
            400.635,
            166.834,
            399.745,
            164.3,
            398.936,
            161.898,
            398.199,
            159.618,
            397.53,
            157.45,
            396.923,
            155.388,
            396.373,
            153.423,
            395.875,
            151.548,
            395.426,
            149.758,
            395.022,
            148.047,
            394.659,
            146.409,
            394.334,
            144.841,
            394.045,
            143.338,
            393.788,
            141.895,
            393.563,
            140.51,
            393.367,
            139.178,
            393.2,
            137.897,
            393.061,
            136.665,
            392.948,
            135.477,
            392.86,
            134.333,
            392.797,
            133.229,
            392.757,
            132.164,
            392.741,
            131.135,
            392.747,
            130.141,
            392.775,
            129.179,
            392.823,
            128.249,
            392.892,
            127.349,
            392.981,
            126.477,
            393.089,
            125.632,
            393.216,
            124.814,
            393.361,
            124.019,
            393.524,
            123.249,
            393.705,
            122.501,
            393.901,
            121.774,
            394.111,
            121.068,
            394.334,
            120.382,
            394.566,
            119.715,
            394.808,
            119.066,
            395.057,
            118.434,
            395.312,
            117.82,
            395.572,
            117.221,
            395.836,
            116.638,
            396.102,
            116.069,
            396.369,
            115.515,
            396.636,
            114.975,
            396.903,
            114.448,
            397.168,
            113.934,
            397.43,
            113.432,
            397.688,
            112.942,
            397.942,
            112.464,
            398.117,
            112.136
          ]
        ]
      },
      {
        "thr": "0.4",
        "curves": [
          [
            -8.31439,
            248.994,
            10.2543,
            240.359,
            27.0978,
            232.529,
            42.449,
            225.395,
            56.5013,
            218.868,
            69.4165,
            212.874,
            81.3309,
            207.351,
            92.3602,
            202.244,
            102.603,
            197.509,
            112.146,
            193.107,
            121.06,
            189.003,
            129.411,
            185.168,
            137.254,
            181.577,
            144.637,
            178.207,
            151.605,
            175.038,
            158.195,
            172.053,
            164.44,
            169.237,
            170.371,
            166.574,
            176.015,
            164.054,
            181.393,
            161.664,
            186.527,
            159.396,
            191.435,
            157.24,
            196.134,
            155.187,
            200.639,
            153.231,
            204.964,
            151.365,
            209.121,
            149.584,
            213.122,
            147.88,
            216.977,
            146.25,
            220.695,
            144.688,
            224.286,
            143.191,
            227.758,
            141.754,
            231.117,
            140.374,
            234.372,
            139.048,
            237.527,
            137.772,
            240.589,
            136.544,
            243.563,
            135.361,
            246.451,
            134.221,
            249.257,
            133.121,
            251.984,
            132.059,
            254.635,
            131.034,
            257.212,
            130.043,
            259.718,
            129.085,
            262.155,
            128.158,
            264.524,
            127.261,
            266.829,
            126.392,
            269.071,
            125.549,
            271.252,
            124.733,
            273.373,
            123.941,
            275.436,
            123.173,
            277.442,
            122.427,
            279.393,
            121.703,
            281.29,
            120.999,
            283.135,
            120.315,
            284.931,
            119.649,
            286.679,
            119.002,
            288.382,
            118.372,
            290.04,
            117.759,
            291.655,
            117.162,
            293.23,
            116.58,
            294.765,
            116.013,
            296.262,
            115.461,
            297.722,
            114.922,
            299.147,
            114.396,
            300.538,
            113.883,
            301.896,
            113.383,
            303.221,
            112.894,
            304.516,
            112.417,
            305.279,
            112.136
          ],
          [
            113.012,
            374.81,
            132.504,
            350.376,
            149.09,
            329.591,
            163.384,
            311.695,
            175.838,
            296.125,
            186.794,
            282.455,
            196.515,
            270.358,
            205.209,
            259.576,
            213.038,
            249.906,
            220.134,
            241.185,
            226.605,
            233.279,
            232.538,
            226.079,
            238.005,
            219.495,
            243.069,
            213.451,
            247.779,
            207.884,
            252.18,
            202.738,
            256.309,
            197.967,
            260.198,
            193.533,
            263.873,
            189.401,
            267.36,
            185.541,
            270.678,
            181.926,
            273.839,
            178.535,
            276.857,
            175.347,
            279.741,
            172.344,
            282.502,
            169.511,
            285.147,
            166.834,
            287.684,
            164.3,
            290.12,
            161.898,
            292.46,
            159.618,
            294.711,
            157.45,
            296.876,
            155.388,
            298.961,
            153.423,
            300.969,
            151.548,
            302.905,
            149.758,
            304.771,
            148.047,
            306.57,
            146.409,
            308.306,
            144.841,
            309.981,
            143.338,
            311.597,
            141.895,
            313.157,
            140.51,
            314.666,
            139.178,
            316.128,
            137.897,
            317.544,
            136.665,
            318.92,
            135.477,
            320.256,
            134.333,
            321.557,
            133.229,
            322.824,
            132.164,
            324.059,
            131.135,
            325.266,
            130.141,
            326.445,
            129.179,
            327.6,
            128.249,
            328.73,
            127.349,
            329.839,
            126.477,
            330.927,
            125.632,
            331.997,
            124.814,
            333.049,
            124.019,
            334.084,
            123.249,
            335.105,
            122.501,
            336.11,
            121.774,
            337.099,
            121.068,
            338.074,
            120.382,
            339.032,
            119.715,
            339.975,
            119.066,
            340.902,
            118.434,
            341.813,
            117.82,
            342.708,
            117.221,
            343.587,
            116.638,
            344.45,
            116.069,
            345.296,
            115.515,
            346.126,
            114.975,
            346.939,
            114.448,
            347.736,
            113.934,
            348.516,
            113.432,
            349.28,
            112.942,
            350.026,
            112.464,
            350.539,
            112.136
          ],
          [
            506.635,
            374.81,
            493.45,
            350.376,
            482.241,
            329.591,
            472.602,
            311.695,
            464.234,
            296.125,
            456.909,
            282.455,
            450.452,
            270.358,
            444.727,
            259.576,
            439.626,
            249.906,
            435.06,
            241.185,
            430.959,
            233.279,
            427.265,
            226.079,
            423.93,
            219.495,
            420.912,
            213.451,
            418.178,
            207.884,
            415.7,
            202.738,
            413.452,
            197.967,
            411.413,
            193.533,
            409.565,
            189.401,
            407.89,
            185.541,
            406.37,
            181.926,
            404.989,
            178.535,
            403.734,
            175.347,
            402.594,
            172.344,
            401.558,
            169.511,
            400.616,
            166.834,
            399.759,
            164.3,
            398.982,
            161.898,
            398.275,
            159.618,
            397.635,
            157.45,
            397.054,
            155.388,
            396.529,
            153.423,
            396.053,
            151.548,
            395.625,
            149.758,
            395.239,
            148.047,
            394.892,
            146.409,
            394.582,
            144.841,
            394.306,
            143.338,
            394.063,
            141.895,
            393.85,
            140.51,
            393.667,
            139.178,
            393.511,
            137.897,
            393.381,
            136.665,
            393.276,
            135.477,
            393.196,
            134.333,
            393.137,
            133.229,
            393.101,
            132.164,
            393.086,
            131.135,
            393.09,
            130.141,
            393.113,
            129.179,
            393.155,
            128.249,
            393.215,
            127.349,
            393.291,
            126.477,
            393.383,
            125.632,
            393.49,
            124.814,
            393.609,
            124.019,
            393.74,
            123.249,
            393.88,
            122.501,
            394.029,
            121.774,
            394.184,
            121.068,
            394.345,
            120.382,
            394.511,
            119.715,
            394.68,
            119.066,
            394.851,
            118.434,
            395.023,
            117.82,
            395.196,
            117.221,
            395.368,
            116.638,
            395.538,
            116.069,
            395.706,
            115.515,
            395.872,
            114.975,
            395.92,
            114.816
          ]
        ]
      }
    ]
  }
}